benchconnect/__init__.py
benchconnect/_augment.py
benchconnect/_cli.py
benchconnect/_finish.py
benchconnect/_post.py
benchconnect/_put.py
benchconnect/_start.py
benchconnect/_submit.py
benchconnect/_version.py
benchconnect/utils.py
tests/__init__.py
tests/test_augment.py
tests/test_cli.py
benchconnect-2023.2.8.dist-info/LICENSE.txt
benchconnect-2023.2.8.dist-info/METADATA
benchconnect-2023.2.8.dist-info/WHEEL
benchconnect-2023.2.8.dist-info/entry_points.txt
benchconnect-2023.2.8.dist-info/top_level.txt
benchconnect-2023.2.8.dist-info/RECORD
