Metadata-Version: 2.1
Name: benchconnect
Version: 2023.2.8
Summary: CLI to Post Benchmark Results to a Conbench Server
Home-page: https://github.com/conbench/conbench/tree/main/benchconnect
Maintainer: Voltron Data
Maintainer-email: conbench@voltrondata.com
Classifier: Programming Language :: Python :: 3.8
Classifier: License :: OSI Approved :: Apache Software License
Requires-Python: >=3.8
License-File: LICENSE.txt
Requires-Dist: benchadapt
Requires-Dist: benchclients
Requires-Dist: click
